{
    "total_proxies": 1,
    "by_type": {
        "vmess": 62
    },
    "by_country": {
        "SG": 2,
        "NL": 19,
        "CA": 4,
        "US": 25,
        "FR": 2,
        "DE": 2,
        "AU": 2,
        "IN": 1,
        "TW": 2,
        "GB": 1,
        "EE": 1,
        "XX": 1
    },
    "by_type_and_country": {
        "vmess": {
            "SG": 2,
            "NL": 19,
            "CA": 4,
            "US": 25,
            "FR": 2,
            "DE": 2,
            "AU": 2,
            "IN": 1,
            "TW": 2,
            "GB": 1,
            "EE": 1,
            "XX": 1
        }
    },
    "generated_at": "2025-09-20T15:11:12+00:00"
}