{
    "total_proxies": 1,
    "by_type": {
        "vmess": 100
    },
    "by_country": {
        "US": 42,
        "NL": 23,
        "CA": 4,
        "IN": 1,
        "AU": 17,
        "FR": 3,
        "GB": 1,
        "DE": 2,
        "EE": 1,
        "HK": 2,
        "CN": 1,
        "TW": 3
    },
    "by_type_and_country": {
        "vmess": {
            "US": 42,
            "NL": 23,
            "CA": 4,
            "IN": 1,
            "AU": 17,
            "FR": 3,
            "GB": 1,
            "DE": 2,
            "EE": 1,
            "HK": 2,
            "CN": 1,
            "TW": 3
        }
    },
    "generated_at": "2025-09-25T06:22:54+00:00"
}