{
    "total_proxies": 1,
    "by_type": {
        "vmess": 100
    },
    "by_country": {
        "US": 35,
        "TW": 3,
        "CA": 6,
        "NL": 29,
        "AU": 17,
        "HK": 3,
        "DE": 2,
        "FR": 3,
        "IN": 1,
        "GB": 1
    },
    "by_type_and_country": {
        "vmess": {
            "US": 35,
            "TW": 3,
            "CA": 6,
            "NL": 29,
            "AU": 17,
            "HK": 3,
            "DE": 2,
            "FR": 3,
            "IN": 1,
            "GB": 1
        }
    },
    "generated_at": "2025-09-28T01:08:01+00:00"
}