{
    "total_proxies": 1,
    "by_type": {
        "vmess": 77
    },
    "by_country": {
        "FR": 5,
        "US": 17,
        "DE": 3,
        "NL": 36,
        "CA": 7,
        "XX": 2,
        "AU": 6,
        "GB": 1
    },
    "by_type_and_country": {
        "vmess": {
            "FR": 5,
            "US": 17,
            "DE": 3,
            "NL": 36,
            "CA": 7,
            "XX": 2,
            "AU": 6,
            "GB": 1
        }
    },
    "generated_at": "2025-11-22T14:11:48+00:00"
}