{
    "total_proxies": 1,
    "by_type": {
        "vmess": 100
    },
    "by_country": {
        "AU": 17,
        "NL": 31,
        "CA": 6,
        "US": 32,
        "FR": 7,
        "DE": 4,
        "BR": 1,
        "XX": 2
    },
    "by_type_and_country": {
        "vmess": {
            "AU": 17,
            "NL": 31,
            "CA": 6,
            "US": 32,
            "FR": 7,
            "DE": 4,
            "BR": 1,
            "XX": 2
        }
    },
    "generated_at": "2025-11-10T20:16:49+00:00"
}