{
    "total_proxies": 1,
    "by_type": {
        "vmess": 100
    },
    "by_country": {
        "US": 38,
        "XX": 7,
        "TW": 2,
        "HK": 3,
        "FR": 3,
        "ZA": 3,
        "NL": 26,
        "AU": 11,
        "CA": 5,
        "DE": 2
    },
    "by_type_and_country": {
        "vmess": {
            "US": 38,
            "XX": 7,
            "TW": 2,
            "HK": 3,
            "FR": 3,
            "ZA": 3,
            "NL": 26,
            "AU": 11,
            "CA": 5,
            "DE": 2
        }
    },
    "generated_at": "2025-10-06T23:12:07+00:00"
}